{
    "lev": 5,
    "data": [
        [
            40,
            {
                "type": "quiz",
                "id": 60
            },
            3484536
        ],
        [
            1,
            {
                "chgtNotion": "N",
                "chgtMatiere": "",
                "mod": "win",
                "type": "quiz",
                "subj": 5,
                "notion": "30020",
                "id": 214,
                "matiere": 5,
                "video": [
                    ""
                ],
                "kp": [
                    "n5_30020"
                ],
                "niv": 0,
                "rate": 0,
                "diff": "7",
                "result": 1,
                "corrSeen": 0
            },
            3467767
        ],
        [
            40,
            {
                "type": "quiz",
                "id": 59
            },
            3450150
        ],
        [
            20,
            {
                "type": "jingle",
                "id": "motiv"
            },
            3433393
        ],
        [
            1,
            {
                "chgtNotion": "Y",
                "chgtMatiere": "Y",
                "mod": "win",
                "type": "quiz",
                "subj": 5,
                "notion": "30020",
                "id": 216,
                "matiere": 5,
                "video": [
                    ""
                ],
                "kp": [
                    "n5_30020"
                ],
                "niv": 0,
                "rate": 0,
                "diff": "8",
                "result": 1,
                "corrSeen": 0
            },
            3417359
        ],
        [
            40,
            {
                "type": "quiz",
                "id": 58
            },
            3399754
        ],
        [
            1,
            {
                "chgtNotion": "N",
                "chgtMatiere": "",
                "mod": "win",
                "type": "quiz",
                "subj": 3,
                "notion": "31040",
                "id": 2719,
                "matiere": 3,
                "video": [
                    ""
                ],
                "kp": [
                    "n3_31040"
                ],
                "niv": 0,
                "rate": 0,
                "diff": "9",
                "result": 1,
                "corrSeen": 0
            },
            3382974
        ],
        [
            40,
            {
                "type": "quiz",
                "id": 57
            },
            3365358
        ],
        [
            10,
            {
                "type": "brick",
                "id": "7192",
                "fun": 1
            },
            3348468
        ],
        [
            20,
            {
                "type": "jingle",
                "id": "brick"
            },
            3331738
        ],
        [
            1,
            {
                "chgtNotion": "N",
                "chgtMatiere": "",
                "mod": "win",
                "type": "quiz",
                "subj": 3,
                "notion": "31040",
                "id": 2689,
                "matiere": 3,
                "video": [
                    ""
                ],
                "kp": [
                    "n3_31040"
                ],
                "niv": 0,
                "rate": 0,
                "diff": "6",
                "result": 1,
                "corrSeen": 0
            },
            3314702
        ],
        [
            40,
            {
                "type": "quiz",
                "id": 56
            },
            3297093
        ],
        [
            1,
            {
                "chgtNotion": "N",
                "chgtMatiere": "",
                "mod": "win",
                "type": "quiz",
                "subj": 3,
                "notion": "31040",
                "id": 2727,
                "matiere": 3,
                "video": [
                    ""
                ],
                "kp": [
                    "n3_31040"
                ],
                "niv": 0,
                "rate": 0,
                "diff": "10",
                "result": 1,
                "corrSeen": 0
            },
            3280139
        ],
        [
            40,
            {
                "type": "quiz",
                "id": 55
            },
            3262530
        ],
        [
            1,
            {
                "chgtNotion": "N",
                "chgtMatiere": "",
                "mod": "win",
                "type": "quiz",
                "subj": 3,
                "notion": "31040",
                "id": 2716,
                "matiere": 3,
                "video": [
                    ""
                ],
                "kp": [
                    "n3_31040"
                ],
                "niv": 0,
                "rate": 0,
                "diff": "9",
                "result": 1,
                "corrSeen": 0
            },
            3245593
        ],
        [
            40,
            {
                "type": "quiz",
                "id": 54
            },
            3227983
        ],
        [
            20,
            {
                "type": "jingle",
                "id": "motiv"
            },
            3211073
        ],
        [
            1,
            {
                "chgtNotion": "N",
                "chgtMatiere": "",
                "mod": "win",
                "type": "quiz",
                "subj": 3,
                "notion": "31040",
                "id": 2725,
                "matiere": 3,
                "video": [
                    ""
                ],
                "kp": [
                    "n3_31040"
                ],
                "niv": 0,
                "rate": 0,
                "diff": "10",
                "result": 1,
                "corrSeen": 0
            },
            3195036
        ],
        [
            40,
            {
                "type": "quiz",
                "id": 53
            },
            3177430
        ],
        [
            1,
            {
                "chgtNotion": "Y",
                "chgtMatiere": "N",
                "mod": "win",
                "type": "quiz",
                "subj": 3,
                "notion": "31040",
                "id": 2712,
                "matiere": 3,
                "video": [
                    ""
                ],
                "kp": [
                    "n3_31040"
                ],
                "niv": 0,
                "rate": 0,
                "diff": "9",
                "result": 1,
                "corrSeen": 0
            },
            3160527
        ],
        [
            40,
            {
                "type": "quiz",
                "id": 52
            },
            3142918
        ],
        [
            1,
            {
                "chgtNotion": "Y",
                "chgtMatiere": "Y",
                "mod": "win",
                "type": "coach",
                "subj": "vocEnglishAI",
                "notion": "17010",
                "id": 337,
                "matiere": 3,
                "video": [
                    ""
                ],
                "kp": [
                    ""
                ],
                "niv": "",
                "rate": 0,
                "diff": "3",
                "result": 1,
                "errors": 0
            },
            3125990
        ],
        [
            40,
            {
                "type": "quiz",
                "id": 51
            },
            3110290
        ],
        [
            20,
            {
                "type": "jingle",
                "id": "mode_progression"
            },
            3093283
        ],
        [
            1,
            {
                "chgtNotion": "Y",
                "chgtMatiere": "N",
                "mod": "cool",
                "type": "coach",
                "subj": "vocEnglishAI",
                "notion": "17010",
                "id": 334,
                "matiere": 3,
                "video": [
                    ""
                ],
                "kp": [
                    ""
                ],
                "niv": "",
                "rate": 1,
                "diff": "3",
                "result": 1,
                "errors": 0
            },
            3075450
        ],
        [
            40,
            {
                "type": "quiz",
                "id": 50
            },
            3059740
        ],
        [
            10,
            {
                "type": "msg",
                "type2": "joke",
                "id": "4483",
                "fun": 1
            },
            3042566
        ],
        [
            20,
            {
                "type": "jingle",
                "id": "joke"
            },
            3025838
        ],
        [
            1,
            {
                "chgtNotion": "Y",
                "chgtMatiere": "Y",
                "mod": "cool",
                "type": "coach",
                "subj": "vocEnglishAI",
                "notion": "17010",
                "id": 277,
                "matiere": 3,
                "video": [
                    ""
                ],
                "kp": [
                    ""
                ],
                "niv": "",
                "rate": null,
                "diff": "3",
                "result": 1,
                "errors": 0
            },
            3009805
        ],
        [
            40,
            {
                "type": "quiz",
                "id": 49
            },
            2994093
        ],
        [
            1,
            {
                "chgtNotion": "Y",
                "chgtMatiere": "Y",
                "mod": "cool",
                "type": "coach",
                "subj": "vocEnglishAI",
                "notion": "17010",
                "id": 141,
                "matiere": 3,
                "video": [
                    ""
                ],
                "kp": [
                    ""
                ],
                "niv": "",
                "rate": 1,
                "diff": "3",
                "result": 1,
                "errors": 0
            },
            2977094
        ],
        [
            40,
            {
                "type": "quiz",
                "id": 48
            },
            2961391
        ],
        [
            1,
            {
                "chgtNotion": "Y",
                "chgtMatiere": "Y",
                "mod": "cool",
                "type": "coach",
                "subj": "vocEnglishAI",
                "notion": "17010",
                "id": 400,
                "matiere": 3,
                "video": [
                    ""
                ],
                "kp": [
                    ""
                ],
                "niv": "",
                "rate": 0,
                "diff": "3",
                "result": 1,
                "errors": 0
            },
            2944365
        ],
        [
            40,
            {
                "type": "quiz",
                "id": 47
            },
            2928663
        ],
        [
            10,
            {
                "type": "brick",
                "id": "7215",
                "fun": 1
            },
            2911678
        ],
        [
            20,
            {
                "type": "jingle",
                "id": "brick"
            },
            2894944
        ],
        [
            1,
            {
                "chgtNotion": "Y",
                "chgtMatiere": "N",
                "mod": "cool",
                "type": "quiz",
                "subj": 1,
                "notion": "44030",
                "id": 6773,
                "matiere": 1,
                "video": [
                    ""
                ],
                "kp": [
                    "n1_44030"
                ],
                "niv": 0,
                "rate": 0,
                "diff": "5",
                "result": 1,
                "corrSeen": 0
            },
            2877896
        ],
        [
            40,
            {
                "type": "quiz",
                "id": 46
            },
            2860293
        ],
        [
            1,
            {
                "chgtNotion": "N",
                "chgtMatiere": "",
                "mod": "cool",
                "type": "quiz",
                "subj": 1,
                "notion": "12040",
                "id": 1629,
                "matiere": 1,
                "video": [
                    "5/5_1_06_01_01_00"
                ],
                "kp": [
                    "5_1_6"
                ],
                "niv": 0,
                "rate": 0,
                "diff": "7",
                "result": 1,
                "corrSeen": 0
            },
            2842715
        ],
        [
            40,
            {
                "type": "quiz",
                "id": 45
            },
            2825106
        ],
        [
            20,
            {
                "type": "jingle",
                "id": "mode_cool"
            },
            2807578
        ],
        [
            1,
            {
                "chgtNotion": "N",
                "chgtMatiere": "",
                "mod": "win",
                "type": "quiz",
                "subj": 1,
                "notion": "12040",
                "id": 1647,
                "matiere": 1,
                "video": [
                    "5/5_1_06_01_01_00"
                ],
                "kp": [
                    "5_1_6"
                ],
                "niv": 0,
                "rate": 0,
                "diff": "10",
                "result": 1,
                "corrSeen": 0
            },
            2789721
        ],
        [
            40,
            {
                "type": "quiz",
                "id": 44
            },
            2772116
        ],
        [
            20,
            {
                "type": "jingle",
                "id": "motiv"
            },
            2754606
        ],
        [
            1,
            {
                "chgtNotion": "N",
                "chgtMatiere": "",
                "mod": "win",
                "type": "quiz",
                "subj": 1,
                "notion": "12040",
                "id": 1639,
                "matiere": 1,
                "video": [
                    "5/5_1_06_01_01_00"
                ],
                "kp": [
                    "5_1_6"
                ],
                "niv": 0,
                "rate": 0,
                "diff": "8",
                "result": 1,
                "corrSeen": 0
            },
            2738556
        ],
        [
            40,
            {
                "type": "quiz",
                "id": 43
            },
            2720948
        ],
        [
            1,
            {
                "chgtNotion": "N",
                "chgtMatiere": "",
                "mod": "win",
                "type": "quiz",
                "subj": 1,
                "notion": "12040",
                "id": 1622,
                "matiere": 1,
                "video": [
                    "5/5_1_06_01_01_00"
                ],
                "kp": [
                    "5_1_6"
                ],
                "niv": 0,
                "rate": 0,
                "diff": "6",
                "result": 1,
                "corrSeen": 0
            },
            2703411
        ],
        [
            40,
            {
                "type": "quiz",
                "id": 42
            },
            2685807
        ],
        [
            1,
            {
                "chgtNotion": "Y",
                "chgtMatiere": "Y",
                "mod": "win",
                "type": "quiz",
                "subj": 1,
                "notion": "12040",
                "id": 1641,
                "matiere": 1,
                "video": [
                    "5/5_1_06_01_01_00"
                ],
                "kp": [
                    "5_1_6"
                ],
                "niv": 0,
                "rate": 0,
                "diff": "9",
                "result": 1,
                "corrSeen": 0
            },
            2668262
        ],
        [
            40,
            {
                "type": "quiz",
                "id": 41
            },
            2650653
        ],
        [
            10,
            {
                "type": "msg",
                "type2": "joke",
                "id": "4250",
                "fun": 1
            },
            2632899
        ],
        [
            20,
            {
                "type": "jingle",
                "id": "joke"
            },
            2616178
        ],
        [
            1,
            {
                "chgtNotion": "N",
                "chgtMatiere": "",
                "mod": "win",
                "type": "quiz",
                "subj": 11,
                "notion": "8020",
                "id": 198,
                "matiere": 11,
                "video": [
                    ""
                ],
                "kp": [
                    "n7_8020"
                ],
                "niv": 0,
                "rate": 0,
                "diff": "8",
                "result": 1,
                "corrSeen": 0
            },
            2598652
        ],
        [
            40,
            {
                "type": "quiz",
                "id": 40
            },
            2581046
        ],
        [
            1,
            {
                "chgtNotion": "N",
                "chgtMatiere": "",
                "mod": "win",
                "type": "quiz",
                "subj": 11,
                "notion": "8020",
                "id": 194,
                "matiere": 11,
                "video": [
                    ""
                ],
                "kp": [
                    "n7_8020"
                ],
                "niv": 0,
                "rate": 0,
                "diff": "6",
                "result": 1,
                "corrSeen": 0
            },
            2564303
        ],
        [
            40,
            {
                "type": "quiz",
                "id": 39
            },
            2546696
        ],
        [
            1,
            {
                "chgtNotion": "N",
                "chgtMatiere": "",
                "mod": "win",
                "type": "quiz",
                "subj": 11,
                "notion": "8020",
                "id": 197,
                "matiere": 11,
                "video": [
                    ""
                ],
                "kp": [
                    "n7_8020"
                ],
                "niv": 0,
                "rate": 0,
                "diff": "7",
                "result": 1,
                "corrSeen": 0
            },
            2529960
        ],
        [
            40,
            {
                "type": "quiz",
                "id": 38
            },
            2512353
        ],
        [
            1,
            {
                "chgtNotion": "N",
                "chgtMatiere": "",
                "mod": "win",
                "type": "quiz",
                "subj": 11,
                "notion": "8020",
                "id": 203,
                "matiere": 11,
                "video": [
                    ""
                ],
                "kp": [
                    "n7_8020"
                ],
                "niv": 0,
                "rate": 0,
                "diff": "10",
                "result": 1,
                "corrSeen": 0
            },
            2495609
        ],
        [
            40,
            {
                "type": "quiz",
                "id": 37
            },
            2478002
        ],
        [
            20,
            {
                "type": "jingle",
                "id": "motiv"
            },
            2461259
        ],
        [
            1,
            {
                "chgtNotion": "N",
                "chgtMatiere": "",
                "mod": "win",
                "type": "quiz",
                "subj": 11,
                "notion": "8020",
                "id": 200,
                "matiere": 11,
                "video": [
                    ""
                ],
                "kp": [
                    "n7_8020"
                ],
                "niv": 0,
                "rate": 0,
                "diff": "9",
                "result": 1,
                "corrSeen": 0
            },
            2445228
        ],
        [
            40,
            {
                "type": "quiz",
                "id": 36
            },
            2427621
        ],
        [
            1,
            {
                "chgtNotion": "Y",
                "chgtMatiere": "N",
                "mod": "win",
                "type": "quiz",
                "subj": 11,
                "notion": "8020",
                "id": 201,
                "matiere": 11,
                "video": [
                    ""
                ],
                "kp": [
                    "n7_8020"
                ],
                "niv": 0,
                "rate": 0,
                "diff": "9",
                "result": 1,
                "corrSeen": 0
            },
            2410860
        ],
        [
            40,
            {
                "type": "quiz",
                "id": 35
            },
            2393250
        ],
        [
            20,
            {
                "type": "jingle",
                "id": "mode_progression"
            },
            2376489
        ],
        [
            10,
            {
                "type": "brick",
                "id": "7218",
                "fun": 1
            },
            2358670
        ],
        [
            20,
            {
                "type": "jingle",
                "id": "brick"
            },
            2341947
        ],
        [
            1,
            {
                "chgtNotion": "Y",
                "chgtMatiere": "Y",
                "mod": "cool",
                "type": "quiz",
                "subj": 11,
                "notion": "1010",
                "id": 2,
                "matiere": 11,
                "video": [
                    ""
                ],
                "kp": [
                    "n7_1010"
                ],
                "niv": 2,
                "rate": 0,
                "diff": "6",
                "result": 1,
                "corrSeen": 0
            },
            2324921
        ],
        [
            40,
            {
                "type": "quiz",
                "id": 34
            },
            2307318
        ],
        [
            1,
            {
                "chgtNotion": "Y",
                "chgtMatiere": "Y",
                "mod": "cool",
                "type": "quiz",
                "subj": 3,
                "notion": "21020",
                "id": 1425,
                "matiere": 3,
                "video": [
                    ""
                ],
                "kp": [
                    "n3_21110"
                ],
                "niv": 2,
                "rate": 0,
                "diff": "5",
                "result": 1,
                "corrSeen": 0
            },
            2290572
        ],
        [
            40,
            {
                "type": "quiz",
                "id": 33
            },
            2272967
        ],
        [
            10,
            {
                "type": "msg",
                "type2": "joke",
                "id": "4504",
                "fun": 1
            },
            2255843
        ],
        [
            20,
            {
                "type": "jingle",
                "id": "joke"
            },
            2239110
        ],
        [
            1,
            {
                "chgtNotion": "Y",
                "chgtMatiere": "N",
                "mod": "cool",
                "type": "quiz",
                "subj": 1,
                "notion": "20040",
                "id": 3218,
                "matiere": 1,
                "video": [
                    "7/7_1_29_01_01_00"
                ],
                "kp": [
                    "7_1_29"
                ],
                "niv": 0,
                "rate": 0,
                "diff": "5",
                "result": 1,
                "corrSeen": 0
            },
            2221561
        ],
        [
            40,
            {
                "type": "quiz",
                "id": 32
            },
            2203954
        ],
        [
            1,
            {
                "chgtNotion": "Y",
                "chgtMatiere": "Y",
                "mod": "cool",
                "type": "quiz",
                "subj": 1,
                "notion": "46030",
                "id": 6954,
                "matiere": 1,
                "video": [
                    ""
                ],
                "kp": [
                    "6_1_9"
                ],
                "niv": 0,
                "rate": 0,
                "diff": "6",
                "result": 1,
                "corrSeen": 0
            },
            2186430
        ],
        [
            40,
            {
                "type": "quiz",
                "id": 31
            },
            2168816
        ],
        [
            1,
            {
                "chgtNotion": "Y",
                "chgtMatiere": "Y",
                "mod": "cool",
                "type": "coach",
                "subj": "vocEnglishAI",
                "notion": "17010",
                "id": 423,
                "matiere": 3,
                "video": [
                    ""
                ],
                "kp": [
                    ""
                ],
                "niv": "",
                "rate": 0,
                "diff": "3",
                "result": 1,
                "errors": 0
            },
            2151281
        ],
        [
            40,
            {
                "type": "quiz",
                "id": 30
            },
            2135571
        ],
        [
            10,
            {
                "type": "brick",
                "id": "7222",
                "fun": 1
            },
            2118577
        ],
        [
            20,
            {
                "type": "jingle",
                "id": "brick"
            },
            2101851
        ],
        [
            1,
            {
                "chgtNotion": "Y",
                "chgtMatiere": "N",
                "mod": "cool",
                "type": "quiz",
                "subj": 2,
                "notion": "6030",
                "id": 950,
                "matiere": 2,
                "video": [
                    ""
                ],
                "kp": [
                    "7_2_27"
                ],
                "niv": 0,
                "rate": 0,
                "diff": "8",
                "result": 1,
                "corrSeen": 0
            },
            2084796
        ],
        [
            40,
            {
                "type": "quiz",
                "id": 29
            },
            2067184
        ],
        [
            1,
            {
                "chgtNotion": "N",
                "chgtMatiere": "",
                "mod": "cool",
                "type": "quiz",
                "subj": 2,
                "notion": "8030",
                "id": 1359,
                "matiere": 2,
                "video": [
                    ""
                ],
                "kp": [
                    "8_2_34"
                ],
                "niv": 0,
                "rate": 0,
                "diff": "8",
                "result": 1,
                "corrSeen": 0
            },
            2049826
        ],
        [
            40,
            {
                "type": "quiz",
                "id": 28
            },
            2032213
        ],
        [
            20,
            {
                "type": "jingle",
                "id": "mode_cool"
            },
            2014908
        ],
        [
            20,
            {
                "type": "jingle",
                "id": "motiv"
            },
            1997076
        ],
        [
            1,
            {
                "chgtNotion": "N",
                "chgtMatiere": "",
                "mod": "win",
                "type": "quiz",
                "subj": 2,
                "notion": "8030",
                "id": 1373,
                "matiere": 2,
                "video": [
                    ""
                ],
                "kp": [
                    "8_2_34"
                ],
                "niv": 0,
                "rate": 0,
                "diff": "10",
                "result": 1,
                "corrSeen": 0
            },
            1981013
        ],
        [
            40,
            {
                "type": "quiz",
                "id": 27
            },
            1963410
        ],
        [
            1,
            {
                "chgtNotion": "N",
                "chgtMatiere": "",
                "mod": "win",
                "type": "quiz",
                "subj": 2,
                "notion": "8030",
                "id": 1375,
                "matiere": 2,
                "video": [
                    ""
                ],
                "kp": [
                    "8_2_34"
                ],
                "niv": 0,
                "rate": 0,
                "diff": "10",
                "result": 1,
                "corrSeen": 0
            },
            1946065
        ],
        [
            40,
            {
                "type": "quiz",
                "id": 26
            },
            1928455
        ],
        [
            1,
            {
                "chgtNotion": "N",
                "chgtMatiere": "",
                "mod": "win",
                "type": "quiz",
                "subj": 2,
                "notion": "8030",
                "id": 1365,
                "matiere": 2,
                "video": [
                    ""
                ],
                "kp": [
                    "8_2_34"
                ],
                "niv": 0,
                "rate": 0,
                "diff": "9",
                "result": 1,
                "corrSeen": 0
            },
            1911117
        ],
        [
            40,
            {
                "type": "quiz",
                "id": 25
            },
            1893512
        ],
        [
            1,
            {
                "chgtNotion": "Y",
                "chgtMatiere": "N",
                "mod": "win",
                "type": "quiz",
                "subj": 2,
                "notion": "8030",
                "id": 1355,
                "matiere": 2,
                "video": [
                    ""
                ],
                "kp": [
                    "8_2_34"
                ],
                "niv": 0,
                "rate": 0,
                "diff": "7",
                "result": 1,
                "corrSeen": 0
            },
            1876172
        ],
        [
            40,
            {
                "type": "quiz",
                "id": 24
            },
            1858565
        ],
        [
            10,
            {
                "type": "msg",
                "type2": "joke",
                "id": "4472",
                "fun": 1
            },
            1841020
        ],
        [
            20,
            {
                "type": "jingle",
                "id": "joke"
            },
            1824299
        ],
        [
            1,
            {
                "chgtNotion": "N",
                "chgtMatiere": "",
                "mod": "win",
                "type": "quiz",
                "subj": 2,
                "notion": "22020",
                "id": 3480,
                "matiere": 2,
                "video": [
                    "8/8_2_07_01_03_00"
                ],
                "kp": [
                    "8_2_22"
                ],
                "niv": 0,
                "rate": 0,
                "diff": "8",
                "result": 1,
                "corrSeen": 0
            },
            1806743
        ],
        [
            40,
            {
                "type": "quiz",
                "id": 23
            },
            1789139
        ],
        [
            1,
            {
                "chgtNotion": "N",
                "chgtMatiere": "",
                "mod": "win",
                "type": "quiz",
                "subj": 2,
                "notion": "22020",
                "id": 3475,
                "matiere": 2,
                "video": [
                    "8/8_2_07_01_03_00"
                ],
                "kp": [
                    "8_2_22"
                ],
                "niv": 0,
                "rate": 0,
                "diff": "7",
                "result": 1,
                "corrSeen": 0
            },
            1771792
        ],
        [
            40,
            {
                "type": "quiz",
                "id": 22
            },
            1754180
        ],
        [
            1,
            {
                "chgtNotion": "N",
                "chgtMatiere": "",
                "mod": "win",
                "type": "quiz",
                "subj": 2,
                "notion": "22020",
                "id": 3469,
                "matiere": 2,
                "video": [
                    "8/8_2_07_01_03_00"
                ],
                "kp": [
                    "8_2_22"
                ],
                "niv": 0,
                "rate": 0,
                "diff": "6",
                "result": 1,
                "corrSeen": 0
            },
            1736812
        ],
        [
            40,
            {
                "type": "quiz",
                "id": 21
            },
            1719200
        ],
        [
            20,
            {
                "type": "jingle",
                "id": "motiv"
            },
            1701864
        ],
        [
            1,
            {
                "chgtNotion": "N",
                "chgtMatiere": "",
                "mod": "win",
                "type": "quiz",
                "subj": 2,
                "notion": "22020",
                "id": 3455,
                "matiere": 2,
                "video": [
                    "8/8_2_07_01_03_00"
                ],
                "kp": [
                    "8_2_22"
                ],
                "niv": 0,
                "rate": 0,
                "diff": "4",
                "result": 1,
                "corrSeen": 0
            },
            1685802
        ],
        [
            40,
            {
                "type": "quiz",
                "id": 20
            },
            1668198
        ],
        [
            1,
            {
                "chgtNotion": "N",
                "chgtMatiere": "",
                "mod": "win",
                "type": "quiz",
                "subj": 2,
                "notion": "22020",
                "id": 3473,
                "matiere": 2,
                "video": [
                    "8/8_2_07_01_03_00"
                ],
                "kp": [
                    "8_2_22"
                ],
                "niv": 0,
                "rate": 0,
                "diff": "7",
                "result": 1,
                "corrSeen": 0
            },
            1650565
        ],
        [
            40,
            {
                "type": "quiz",
                "id": 19
            },
            1632962
        ],
        [
            1,
            {
                "chgtNotion": "Y",
                "chgtMatiere": "Y",
                "mod": "win",
                "type": "quiz",
                "subj": 2,
                "notion": "22020",
                "id": 3468,
                "matiere": 2,
                "video": [
                    "8/8_2_07_01_03_00"
                ],
                "kp": [
                    "8_2_22"
                ],
                "niv": 0,
                "rate": 0,
                "diff": "6",
                "result": 1,
                "corrSeen": 0
            },
            1615571
        ],
        [
            40,
            {
                "type": "quiz",
                "id": 18
            },
            1597960
        ],
        [
            20,
            {
                "type": "jingle",
                "id": "mode_progression"
            },
            1580486
        ],
        [
            10,
            {
                "type": "brick",
                "id": "7388",
                "fun": 1
            },
            1562666
        ],
        [
            20,
            {
                "type": "jingle",
                "id": "brick"
            },
            1545938
        ],
        [
            1,
            {
                "chgtNotion": "Y",
                "chgtMatiere": "Y",
                "mod": "cool",
                "type": "quiz",
                "subj": 0,
                "notion": 98,
                "id": 1404,
                "matiere": 0,
                "video": [],
                "kp": [],
                "niv": "",
                "rate": 0,
                "diff": "4",
                "result": 1,
                "corrSeen": 0
            },
            1485983
        ],
        [
            40,
            {
                "type": "quiz",
                "id": 17
            },
            1350976
        ],
        [
            20,
            {
                "type": "jingle",
                "id": "think"
            },
            1111984
        ],
        [
            1,
            {
                "chgtNotion": "Y",
                "chgtMatiere": "Y",
                "mod": "cool",
                "type": "quiz",
                "subj": 1,
                "notion": "12030",
                "id": 1601,
                "matiere": 1,
                "video": [
                    ""
                ],
                "kp": [
                    "5_1_2"
                ],
                "niv": 0,
                "rate": 0,
                "diff": "6",
                "result": 1,
                "corrSeen": 0
            },
            1090978
        ],
        [
            40,
            {
                "type": "quiz",
                "id": 16
            },
            1072981
        ],
        [
            10,
            {
                "type": "msg",
                "type2": "joke",
                "id": "4473",
                "fun": 1
            },
            1050971
        ],
        [
            20,
            {
                "type": "jingle",
                "id": "joke"
            },
            1029981
        ],
        [
            1,
            {
                "chgtNotion": "Y",
                "chgtMatiere": "Y",
                "mod": "cool",
                "type": "coach",
                "subj": "vocEnglishAI",
                "notion": "17010",
                "id": 407,
                "matiere": 3,
                "video": [
                    ""
                ],
                "kp": [
                    ""
                ],
                "niv": "",
                "rate": 0,
                "diff": "3",
                "result": 1,
                "errors": 0
            },
            1008978
        ],
        [
            40,
            {
                "type": "quiz",
                "id": 15
            },
            991984
        ],
        [
            1,
            {
                "chgtNotion": "Y",
                "chgtMatiere": "Y",
                "mod": "cool",
                "type": "coach",
                "subj": "vocEnglishAI",
                "notion": "17010",
                "id": 328,
                "matiere": 3,
                "video": [
                    ""
                ],
                "kp": [
                    ""
                ],
                "niv": "",
                "rate": 0,
                "diff": "3",
                "result": 1,
                "errors": 0
            },
            970978
        ],
        [
            40,
            {
                "type": "quiz",
                "id": 14
            },
            953973
        ],
        [
            20,
            {
                "type": "jingle",
                "id": "motiv"
            },
            932983
        ],
        [
            1,
            {
                "chgtNotion": "Y",
                "chgtMatiere": "Y",
                "mod": "cool",
                "type": "quiz",
                "subj": 2,
                "notion": "6050",
                "id": 1025,
                "matiere": 2,
                "video": [
                    ""
                ],
                "kp": [
                    "7_2_27"
                ],
                "niv": 0,
                "rate": 0,
                "diff": "4",
                "result": 1,
                "corrSeen": 0
            },
            913980
        ],
        [
            40,
            {
                "type": "quiz",
                "id": 13
            },
            895984
        ],
        [
            10,
            {
                "type": "brick",
                "id": "7192",
                "fun": 1
            },
            877349
        ],
        [
            20,
            {
                "type": "jingle",
                "id": "brick"
            },
            720984
        ],
        [
            1,
            {
                "chgtNotion": "Y",
                "chgtMatiere": "N",
                "mod": "cool",
                "type": "quiz",
                "subj": 6,
                "notion": "12010",
                "id": 481,
                "matiere": 6,
                "video": [
                    ""
                ],
                "kp": [
                    "n6_12010"
                ],
                "niv": 0,
                "rate": 0,
                "diff": "6",
                "result": 1,
                "corrSeen": 0
            },
            654984
        ],
        [
            40,
            {
                "type": "quiz",
                "id": 12
            },
            636975
        ],
        [
            1,
            {
                "chgtNotion": "N",
                "chgtMatiere": "",
                "mod": "cool",
                "type": "quiz",
                "subj": 6,
                "notion": "8015",
                "id": 376,
                "matiere": 6,
                "video": [
                    ""
                ],
                "kp": [
                    "n6_8015"
                ],
                "niv": 0,
                "rate": 0,
                "diff": "6",
                "result": 1,
                "corrSeen": 0
            },
            615984
        ],
        [
            40,
            {
                "type": "quiz",
                "id": 11
            },
            597976
        ],
        [
            20,
            {
                "type": "jingle",
                "id": "mode_cool"
            },
            576971
        ],
        [
            1,
            {
                "chgtNotion": "N",
                "chgtMatiere": "",
                "mod": "win",
                "type": "quiz",
                "subj": 6,
                "notion": "8015",
                "id": 380,
                "matiere": 6,
                "video": [
                    ""
                ],
                "kp": [
                    "n6_8015"
                ],
                "niv": 0,
                "rate": 0,
                "diff": "8",
                "result": 1,
                "corrSeen": 0
            },
            554982
        ],
        [
            40,
            {
                "type": "quiz",
                "id": 10
            },
            536984
        ],
        [
            10,
            {
                "type": "msg",
                "type2": "joke",
                "id": "4509",
                "fun": 1
            },
            515971
        ],
        [
            20,
            {
                "type": "jingle",
                "id": "joke"
            },
            494975
        ],
        [
            1,
            {
                "chgtNotion": "N",
                "chgtMatiere": "",
                "mod": "win",
                "type": "quiz",
                "subj": 6,
                "notion": "8015",
                "id": 385,
                "matiere": 6,
                "video": [
                    ""
                ],
                "kp": [
                    "n6_8015"
                ],
                "niv": 0,
                "rate": 0,
                "diff": "10",
                "result": 1,
                "corrSeen": 0
            },
            474987
        ],
        [
            40,
            {
                "type": "quiz",
                "id": 9
            },
            456972
        ],
        [
            1,
            {
                "chgtNotion": "N",
                "chgtMatiere": "",
                "mod": "win",
                "type": "quiz",
                "subj": 6,
                "notion": "8015",
                "id": 383,
                "matiere": 6,
                "video": [
                    ""
                ],
                "kp": [
                    "n6_8015"
                ],
                "niv": 0,
                "rate": 0,
                "diff": "9",
                "result": 1,
                "corrSeen": 0
            },
            435980
        ],
        [
            40,
            {
                "type": "quiz",
                "id": 8
            },
            417257
        ],
        [
            1,
            {
                "chgtNotion": "Y",
                "chgtMatiere": "Y",
                "mod": "win",
                "type": "quiz",
                "subj": 6,
                "notion": "8015",
                "id": 386,
                "matiere": 6,
                "video": [
                    ""
                ],
                "kp": [
                    "n6_8015"
                ],
                "niv": 0,
                "rate": 0,
                "diff": "10",
                "result": 1,
                "corrSeen": 0
            },
            400508
        ],
        [
            40,
            {
                "type": "quiz",
                "id": 7
            },
            382903
        ],
        [
            20,
            {
                "type": "jingle",
                "id": "think"
            },
            366149
        ],
        [
            1,
            {
                "chgtNotion": "N",
                "chgtMatiere": "",
                "mod": "win",
                "type": "quiz",
                "subj": 1,
                "notion": "15080",
                "id": 2212,
                "matiere": 1,
                "video": [
                    ""
                ],
                "kp": [
                    "5_1_10"
                ],
                "niv": 1,
                "rate": 0,
                "diff": "9",
                "result": 1,
                "corrSeen": 0
            },
            348595
        ],
        [
            40,
            {
                "type": "quiz",
                "id": 6
            },
            330983
        ],
        [
            1,
            {
                "chgtNotion": "N",
                "chgtMatiere": "",
                "mod": "win",
                "type": "quiz",
                "subj": 1,
                "notion": "15080",
                "id": 2215,
                "matiere": 1,
                "video": [
                    ""
                ],
                "kp": [
                    "5_1_10"
                ],
                "niv": 1,
                "rate": 0,
                "diff": "9",
                "result": 1,
                "corrSeen": 0
            },
            231984
        ],
        [
            40,
            {
                "type": "quiz",
                "id": 5
            },
            213984
        ],
        [
            1,
            {
                "chgtNotion": "N",
                "chgtMatiere": "",
                "mod": "win",
                "type": "quiz",
                "subj": 1,
                "notion": "15080",
                "id": 2213,
                "matiere": 1,
                "video": [
                    ""
                ],
                "kp": [
                    "5_1_10"
                ],
                "niv": 1,
                "rate": 0,
                "diff": "9",
                "result": 1,
                "corrSeen": 0
            },
            192979
        ],
        [
            40,
            {
                "type": "quiz",
                "id": 4
            },
            174983
        ],
        [
            1,
            {
                "chgtNotion": "N",
                "chgtMatiere": "",
                "mod": "win",
                "type": "quiz",
                "subj": 1,
                "notion": "15080",
                "id": 2217,
                "matiere": 1,
                "video": [
                    ""
                ],
                "kp": [
                    "5_1_10"
                ],
                "niv": 1,
                "rate": 0,
                "diff": "9",
                "result": 1,
                "corrSeen": 0
            },
            153984
        ],
        [
            40,
            {
                "type": "quiz",
                "id": 3
            },
            135977
        ],
        [
            1,
            {
                "chgtNotion": "N",
                "chgtMatiere": "",
                "mod": "win",
                "type": "quiz",
                "subj": 1,
                "notion": "15080",
                "id": 2216,
                "matiere": 1,
                "video": [
                    ""
                ],
                "kp": [
                    "5_1_10"
                ],
                "niv": 1,
                "rate": 0,
                "diff": "9",
                "result": 1,
                "corrSeen": 0
            },
            117849
        ],
        [
            40,
            {
                "type": "quiz",
                "id": 2
            },
            100232
        ],
        [
            1,
            {
                "chgtNotion": "Y",
                "chgtMatiere": "Y",
                "mod": "win",
                "type": "quiz",
                "subj": 1,
                "notion": "15080",
                "id": 2214,
                "matiere": 1,
                "video": [
                    ""
                ],
                "kp": [
                    "5_1_10"
                ],
                "niv": 1,
                "rate": 0,
                "diff": "9",
                "result": 1,
                "corrSeen": 0
            },
            81260
        ],
        [
            40,
            {
                "type": "quiz",
                "id": 1
            },
            63630
        ],
        [
            20,
            {
                "type": "jingle",
                "id": "mode_progression"
            },
            43026
        ],
        [
            10,
            {
                "type": "wilo"
            },
            24992
        ],
        [
            20,
            {
                "type": "jingle",
                "id": "start"
            },
            8267
        ]
    ]
}